eucal/__init__.py
eucal/__main__.py
eucal/eucal.py
eucal-0.1.5.dist-info/entry_points.txt
eucal-0.1.5.dist-info/METADATA
eucal-0.1.5.dist-info/WHEEL
eucal-0.1.5.dist-info/RECORD
