Metadata-Version: 2.3
Name: eucal
Version: 0.1.5
Summary: Evaluation & Utilization of Clocked Activity Logs
Requires-Python: >=3.11
Classifier: Programming Language :: Python :: 3
Classifier: Programming Language :: Python :: 3.11
Classifier: Programming Language :: Python :: 3.12
Classifier: Programming Language :: Python :: 3.13
Requires-Dist: click (>=8.2.1)
Requires-Dist: pdfplumber (>=0.11.7)
